thelightscope.py
thelightscope-0.0.1.dist-info/licenses/LICENSE
thelightscope-0.0.1.dist-info/METADATA
thelightscope-0.0.1.dist-info/WHEEL
thelightscope-0.0.1.dist-info/top_level.txt
thelightscope-0.0.1.dist-info/RECORD
