Metadata-Version: 2.4
Name: thelightscope
Version: 0.0.1
Summary: thelightscope cybersecurity research application
Author-email: Eric Kapitanski <e@alumni.usc.edu>
License-Expression: GPL-3.0-only
Project-URL: Homepage, https://thelightscope.com
Project-URL: Issues, https://thelightscope.com
Classifier: Programming Language :: Python :: 3
Classifier: Operating System :: OS Independent
Requires-Python: >=3.8
License-File: LICENSE
Requires-Dist: psutil==7.0.0
Requires-Dist: python-libpcap==0.5.2
Requires-Dist: requests==2.32.3
Requires-Dist: scapy==2.6.1
Requires-Dist: urllib3==2.2.3
Dynamic: license-file
